partial_span_processor/__init__.py
partial_span_processor/peekable_queue.py
partial_span_processor-0.0.9.dist-info/licenses/LICENSE
partial_span_processor-0.0.9.dist-info/METADATA
partial_span_processor-0.0.9.dist-info/WHEEL
partial_span_processor-0.0.9.dist-info/top_level.txt
partial_span_processor-0.0.9.dist-info/RECORD
