Metadata-Version: 2.4
Name: partial_span_processor
Version: 0.0.9
Summary: OTEL Python SDK extension supporting partial spans
Author-email: Mladjan Gadzic <gadzic.mladjan@gmail.com>
License: Apache-2.0
Project-URL: Homepage, https://github.com/G-Research/otel-partial-python
Classifier: Programming Language :: Python :: 3
Classifier: Operating System :: OS Independent
Requires-Python: >=3.8
License-File: LICENSE
Requires-Dist: opentelemetry-api
Requires-Dist: opentelemetry-exporter-otlp
Requires-Dist: opentelemetry-exporter-otlp-proto-common
Requires-Dist: opentelemetry-exporter-otlp-proto-grpc
Requires-Dist: opentelemetry-exporter-otlp-proto-http
Requires-Dist: opentelemetry-proto
Requires-Dist: opentelemetry-sdk
Requires-Dist: opentelemetry-semantic-conventions
Dynamic: license-file
